chatgdb/__init__.py
chatgdb/cli.py
chatgdb/gdb.py
chatgdb/lldb.py
chatgdb/utils.py
chatgdb-1.2.0.dist-info/LICENSE
chatgdb-1.2.0.dist-info/METADATA
chatgdb-1.2.0.dist-info/WHEEL
chatgdb-1.2.0.dist-info/entry_points.txt
chatgdb-1.2.0.dist-info/RECORD
