Metadata-Version: 2.1
Name: chatgdb
Version: 1.2.0
Summary: Harness the power of ChatGPT directly inside the GDB debugger!
Home-page: https://github.com/pgosar/chatgdb
License: MIT
Keywords: gdb,debugger,chatgpt
Author: Pranay Gosar
Author-email: gosarpranay@gmail.com
Requires-Python: >=3.3,<4.0
Classifier: License :: OSI Approved :: MIT License
Classifier: Programming Language :: Python :: 3
Classifier: Programming Language :: Python :: 3.4
Classifier: Programming Language :: Python :: 3.5
Classifier: Programming Language :: Python :: 3.6
Classifier: Programming Language :: Python :: 3.7
Classifier: Programming Language :: Python :: 3.8
Classifier: Programming Language :: Python :: 3.9
Classifier: Programming Language :: Python :: 3.10
Classifier: Programming Language :: Python :: 3.11
Project-URL: Bug Tracker, https://github.com/pgosar/chatgdb/issues
Project-URL: Repository, https://github.com/pgosar/chatgdb
